LICENSE.txt
setup.py
Ahmed122122122323.egg-info/PKG-INFO
Ahmed122122122323.egg-info/SOURCES.txt
Ahmed122122122323.egg-info/dependency_links.txt
Ahmed122122122323.egg-info/top_level.txt
code/__init__.py
code/categorical_encoder.py
code/changing_value.py
code/data_frame_loader.py
code/data_frame_modifier.py
code/data_sorter.py
code/data_type_converter.py
code/date_time_handler.py
code/feature_engineer.py
code/missing_value_handler.py
code/outlier_handler.py
code/scaler.py
code/text_cleaner.py