Metadata-Version: 2.1
Name: Ahmed122122122323
Version: 0.1
Summary: Data Preprocessing
Home-page: UNKNOWN
Author: MHD ALHABEB ALSHALAH, Ahmed Emad Elsayed Mohamed Abdelfattah,MOHAMED RAGAB ABDELFATTAH ABDELFADEEL
License: UNKNOWN
Platform: UNKNOWN
Classifier: Programming Language :: Python :: 3
Classifier: Operating System :: OS Independent 
Classifier: License :: OSI Approved :: MIT License
License-File: LICENSE.txt
